cdktf_cdktf_provider_tfe/__init__.py
cdktf_cdktf_provider_tfe/py.typed
cdktf_cdktf_provider_tfe/_jsii/__init__.py
cdktf_cdktf_provider_tfe/_jsii/provider-tfe@12.5.0.jsii.tgz
cdktf_cdktf_provider_tfe/admin_organization_settings/__init__.py
cdktf_cdktf_provider_tfe/agent_pool/__init__.py
cdktf_cdktf_provider_tfe/agent_pool_allowed_projects/__init__.py
cdktf_cdktf_provider_tfe/agent_pool_allowed_workspaces/__init__.py
cdktf_cdktf_provider_tfe/agent_pool_excluded_workspaces/__init__.py
cdktf_cdktf_provider_tfe/agent_token/__init__.py
cdktf_cdktf_provider_tfe/audit_trail_token/__init__.py
cdktf_cdktf_provider_tfe/aws_oidc_configuration/__init__.py
cdktf_cdktf_provider_tfe/azure_oidc_configuration/__init__.py
cdktf_cdktf_provider_tfe/data_retention_policy/__init__.py
cdktf_cdktf_provider_tfe/data_tfe_agent_pool/__init__.py
cdktf_cdktf_provider_tfe/data_tfe_github_app_installation/__init__.py
cdktf_cdktf_provider_tfe/data_tfe_hyok_customer_key_version/__init__.py
cdktf_cdktf_provider_tfe/data_tfe_hyok_encrypted_data_key/__init__.py
cdktf_cdktf_provider_tfe/data_tfe_ip_ranges/__init__.py
cdktf_cdktf_provider_tfe/data_tfe_no_code_module/__init__.py
cdktf_cdktf_provider_tfe/data_tfe_oauth_client/__init__.py
cdktf_cdktf_provider_tfe/data_tfe_organization/__init__.py
cdktf_cdktf_provider_tfe/data_tfe_organization_members/__init__.py
cdktf_cdktf_provider_tfe/data_tfe_organization_membership/__init__.py
cdktf_cdktf_provider_tfe/data_tfe_organization_run_task/__init__.py
cdktf_cdktf_provider_tfe/data_tfe_organization_run_task_global_settings/__init__.py
cdktf_cdktf_provider_tfe/data_tfe_organization_tags/__init__.py
cdktf_cdktf_provider_tfe/data_tfe_organizations/__init__.py
cdktf_cdktf_provider_tfe/data_tfe_outputs/__init__.py
cdktf_cdktf_provider_tfe/data_tfe_policy_set/__init__.py
cdktf_cdktf_provider_tfe/data_tfe_project/__init__.py
cdktf_cdktf_provider_tfe/data_tfe_projects/__init__.py
cdktf_cdktf_provider_tfe/data_tfe_registry_gpg_key/__init__.py
cdktf_cdktf_provider_tfe-12.5.0.dist-info/LICENSE
cdktf_cdktf_provider_tfe-12.5.0.dist-info/METADATA
cdktf_cdktf_provider_tfe-12.5.0.dist-info/WHEEL
cdktf_cdktf_provider_tfe-12.5.0.dist-info/top_level.txt
cdktf_cdktf_provider_tfe-12.5.0.dist-info/RECORD
